README.md
setup.cfg
setup.py
duckgoose/__init__.py
duckgoose/cam.py
duckgoose/image_classification_bootstrap.py
duckgoose.egg-info/PKG-INFO
duckgoose.egg-info/SOURCES.txt
duckgoose.egg-info/dependency_links.txt
duckgoose.egg-info/requires.txt
duckgoose.egg-info/top_level.txt