Metadata-Version: 1.1
Name: duckgoose
Version: 0.1.7
Summary: Utility functions for the fast ai mooc
Home-page: http://github.com/svenski/duckgoose
Author: Sergiusz Bleja
Author-email: duckgoose@bleja.org
License: MIT
Download-URL: https://github.com/svenski/duckgoose/archive/0.1.6.tar.gz
Keywords: fastai,image-classification,deep-learning,class-activation-maps
Platform: UNKNOWN
